ramlizer
