Metadata-Version: 1.0
Name: ramlizer
Version: 0.1.4
Summary: A parser for the RAML (RESTful API Modeling Language) file format.
Home-page: https://github.com/SandyChapman/ramlizer
Author: Sandy Chapman
Author-email: sandychapman@gmail.com
License: MIT
Platform: UNKNOWN
